pytest_assertutil/__init__.py
pytest_assertutil/test_util.py
pytest_util/__init__.py
pytest_util/test_util.py
tests/__init__.py
tests/test_assert_equal.py
pytest_assertutil-0.0.2.dist-info/LICENSE
pytest_assertutil-0.0.2.dist-info/METADATA
pytest_assertutil-0.0.2.dist-info/WHEEL
pytest_assertutil-0.0.2.dist-info/top_level.txt
pytest_assertutil-0.0.2.dist-info/RECORD
