Metadata-Version: 2.1
Name: pytest-assertutil
Version: 0.0.2
Summary: pytest-assertutil
Home-page: https://github.com/xyloon/pytest-assertutil
Author: xyloon
Author-email: xyloon@gmail.com
License: MIT
Platform: UNKNOWN
Classifier: Programming Language :: Python :: 3
Classifier: License :: OSI Approved :: MIT License
Classifier: Operating System :: OS Independent
